{
  "architecture": "llama",
  "num_blocks": 30,
  "blocks": [
    {
      "block_idx": 0,
      "attention": {
        "num_params": 884736,
        "eigenvalues": [
          647.8482666015625,
          9.503613471984863,
          9.464936390202183e-09,
          0.0,
          0.0,
          0.0,
          0.0,
          0.0,
          0.0,
          0.0,
          0.0,
          0.0,
          0.0,
          0.0,
          0.0,
          0.0,
          0.0,
          0.0,
          0.0,
          0.0
        ],
        "top": 647.8482666015625,
        "bottom": 0.0,
        "median": 0.0,
        "trace": 657.3518676757812
      },
      "mlp": {
        "num_params": 2654208,
        "eigenvalues": [
          299.1346435546875,
          7.595236301422119,
          1.6152279513903522e-08,
          7.771969832685921e-18,
          0.0,
          0.0,
          0.0,
          0.0,
          0.0,
          0.0,
          0.0,
          0.0,
          0.0,
          0.0,
          0.0,
          0.0,
          0.0,
          0.0,
          0.0,
          0.0
        ],
        "top": 299.1346435546875,
        "bottom": 0.0,
        "median": 0.0,
        "trace": 306.7298889160156
      }
    },
    {
      "block_idx": 1,
      "attention": {
        "num_params": 884736,
        "eigenvalues": [
          531.3629150390625,
          13.22708511352539,
          7.3471642103584145e-09,
          0.0,
          0.0,
          0.0,
          0.0,
          0.0,
          0.0,
          0.0,
          0.0,
          0.0,
          0.0,
          0.0,
          0.0,
          0.0,
          0.0,
          0.0,
          0.0,
          0.0
        ],
        "top": 531.3629150390625,
        "bottom": 0.0,
        "median": 0.0,
        "trace": 544.5900268554688
      },
      "mlp": {
        "num_params": 2654208,
        "eigenvalues": [
          212.1088409423828,
          4.8170952796936035,
          9.3198178063858e-09,
          2.864306762100441e-17,
          0.0,
          0.0,
          0.0,
          0.0,
          0.0,
          0.0,
          0.0,
          0.0,
          0.0,
          0.0,
          0.0,
          0.0,
          0.0,
          0.0,
          0.0,
          0.0
        ],
        "top": 212.1088409423828,
        "bottom": 0.0,
        "median": 0.0,
        "trace": 216.92593383789062
      }
    },
    {
      "block_idx": 2,
      "attention": {
        "num_params": 884736,
        "eigenvalues": [
          339.0059509277344,
          9.83458423614502,
          1.5631316685471575e-08,
          0.0,
          0.0,
          0.0,
          0.0,
          0.0,
          0.0,
          0.0,
          0.0,
          0.0,
          0.0,
          0.0,
          0.0,
          0.0,
          0.0,
          0.0,
          0.0,
          0.0
        ],
        "top": 339.0059509277344,
        "bottom": 0.0,
        "median": 0.0,
        "trace": 348.8405456542969
      },
      "mlp": {
        "num_params": 2654208,
        "eigenvalues": [
          238.18165588378906,
          4.365434169769287,
          5.625280685706002e-09,
          4.936978889161758e-19,
          0.0,
          0.0,
          0.0,
          0.0,
          0.0,
          0.0,
          0.0,
          0.0,
          0.0,
          0.0,
          0.0,
          0.0,
          0.0,
          0.0,
          0.0,
          0.0
        ],
        "top": 238.18165588378906,
        "bottom": 0.0,
        "median": 0.0,
        "trace": 242.54708862304688
      }
    },
    {
      "block_idx": 3,
      "attention": {
        "num_params": 884736,
        "eigenvalues": [
          348.5380554199219,
          6.607731342315674,
          6.696862620003685e-09,
          2.6623937633543213e-19,
          0.0,
          0.0,
          0.0,
          0.0,
          0.0,
          0.0,
          0.0,
          0.0,
          0.0,
          0.0,
          0.0,
          0.0,
          0.0,
          0.0,
          0.0,
          0.0
        ],
        "top": 348.5380554199219,
        "bottom": 0.0,
        "median": 0.0,
        "trace": 355.1457824707031
      },
      "mlp": {
        "num_params": 2654208,
        "eigenvalues": [
          27.43498420715332,
          0.6690043807029724,
          2.1225792234957908e-09,
          0.0,
          0.0,
          0.0,
          0.0,
          0.0,
          0.0,
          0.0,
          0.0,
          0.0,
          0.0,
          0.0,
          0.0,
          0.0,
          0.0,
          0.0,
          0.0,
          0.0
        ],
        "top": 27.43498420715332,
        "bottom": 0.0,
        "median": 0.0,
        "trace": 28.103988647460938
      }
    },
    {
      "block_idx": 4,
      "attention": {
        "num_params": 884736,
        "eigenvalues": [
          147.0190887451172,
          2.0785670280456543,
          4.9271884350332584e-09,
          5.3752599163375205e-18,
          0.0,
          0.0,
          0.0,
          0.0,
          0.0,
          0.0,
          0.0,
          0.0,
          0.0,
          0.0,
          0.0,
          0.0,
          0.0,
          0.0,
          0.0,
          0.0
        ],
        "top": 147.0190887451172,
        "bottom": 0.0,
        "median": 0.0,
        "trace": 149.09765625
      },
      "mlp": {
        "num_params": 2654208,
        "eigenvalues": [
          30.08229637145996,
          0.3508131802082062,
          6.106843503106418e-11,
          0.0,
          0.0,
          0.0,
          0.0,
          0.0,
          0.0,
          0.0,
          0.0,
          0.0,
          0.0,
          0.0,
          0.0,
          0.0,
          0.0,
          0.0,
          0.0,
          0.0
        ],
        "top": 30.08229637145996,
        "bottom": 0.0,
        "median": 0.0,
        "trace": 30.433109283447266
      }
    },
    {
      "block_idx": 5,
      "attention": {
        "num_params": 884736,
        "eigenvalues": [
          108.31830596923828,
          0.832165002822876,
          6.632312032905929e-09,
          0.0,
          0.0,
          0.0,
          0.0,
          0.0,
          0.0,
          0.0,
          0.0,
          0.0,
          0.0,
          0.0,
          0.0,
          0.0,
          0.0,
          0.0,
          0.0,
          0.0
        ],
        "top": 108.31830596923828,
        "bottom": 0.0,
        "median": 0.0,
        "trace": 109.15047454833984
      },
      "mlp": {
        "num_params": 2654208,
        "eigenvalues": [
          26.583101272583008,
          0.2540021240711212,
          1.5918104612211437e-09,
          6.175257967755014e-17,
          0.0,
          0.0,
          0.0,
          0.0,
          0.0,
          0.0,
          0.0,
          0.0,
          0.0,
          0.0,
          0.0,
          0.0,
          0.0,
          0.0,
          0.0,
          0.0
        ],
        "top": 26.583101272583008,
        "bottom": 0.0,
        "median": 0.0,
        "trace": 26.83710289001465
      }
    },
    {
      "block_idx": 6,
      "attention": {
        "num_params": 884736,
        "eigenvalues": [
          93.86283111572266,
          0.7141733169555664,
          8.309765320291262e-09,
          5.565609891717611e-18,
          0.0,
          0.0,
          0.0,
          0.0,
          0.0,
          0.0,
          0.0,
          0.0,
          0.0,
          0.0,
          0.0,
          0.0,
          0.0,
          0.0,
          0.0,
          0.0
        ],
        "top": 93.86283111572266,
        "bottom": 0.0,
        "median": 0.0,
        "trace": 94.5770034790039
      },
      "mlp": {
        "num_params": 2654208,
        "eigenvalues": [
          15.740886688232422,
          0.18017666041851044,
          5.885109066738892e-10,
          0.0,
          0.0,
          0.0,
          0.0,
          0.0,
          0.0,
          0.0,
          0.0,
          0.0,
          0.0,
          0.0,
          0.0,
          0.0,
          0.0,
          0.0,
          0.0,
          0.0
        ],
        "top": 15.740886688232422,
        "bottom": 0.0,
        "median": 0.0,
        "trace": 15.921063423156738
      }
    },
    {
      "block_idx": 7,
      "attention": {
        "num_params": 884736,
        "eigenvalues": [
          57.76177978515625,
          0.6035024523735046,
          1.1491587237344447e-08,
          3.59150448237102e-18,
          0.0,
          0.0,
          0.0,
          0.0,
          0.0,
          0.0,
          0.0,
          0.0,
          0.0,
          0.0,
          0.0,
          0.0,
          0.0,
          0.0,
          0.0,
          0.0
        ],
        "top": 57.76177978515625,
        "bottom": 0.0,
        "median": 0.0,
        "trace": 58.36528396606445
      },
      "mlp": {
        "num_params": 2654208,
        "eigenvalues": [
          12.634958267211914,
          0.13104026019573212,
          2.3255752878981184e-10,
          0.0,
          0.0,
          0.0,
          0.0,
          0.0,
          0.0,
          0.0,
          0.0,
          0.0,
          0.0,
          0.0,
          0.0,
          0.0,
          0.0,
          0.0,
          0.0,
          0.0
        ],
        "top": 12.634958267211914,
        "bottom": 0.0,
        "median": 0.0,
        "trace": 12.765998840332031
      }
    },
    {
      "block_idx": 8,
      "attention": {
        "num_params": 884736,
        "eigenvalues": [
          49.342472076416016,
          0.29506221413612366,
          9.26490262287416e-09,
          0.0,
          0.0,
          0.0,
          0.0,
          0.0,
          0.0,
          0.0,
          0.0,
          0.0,
          0.0,
          0.0,
          0.0,
          0.0,
          0.0,
          0.0,
          0.0,
          0.0
        ],
        "top": 49.342472076416016,
        "bottom": 0.0,
        "median": 0.0,
        "trace": 49.637535095214844
      },
      "mlp": {
        "num_params": 2654208,
        "eigenvalues": [
          20.604379653930664,
          0.15734122693538666,
          6.20008211438261e-10,
          0.0,
          0.0,
          0.0,
          0.0,
          0.0,
          0.0,
          0.0,
          0.0,
          0.0,
          0.0,
          0.0,
          0.0,
          0.0,
          0.0,
          0.0,
          0.0,
          0.0
        ],
        "top": 20.604379653930664,
        "bottom": 0.0,
        "median": 0.0,
        "trace": 20.761720657348633
      }
    },
    {
      "block_idx": 9,
      "attention": {
        "num_params": 884736,
        "eigenvalues": [
          18.225051879882812,
          0.19199657440185547,
          1.2323038145467535e-09,
          5.102021066905635e-19,
          0.0,
          0.0,
          0.0,
          0.0,
          0.0,
          0.0,
          0.0,
          0.0,
          0.0,
          0.0,
          0.0,
          0.0,
          0.0,
          0.0,
          0.0,
          0.0
        ],
        "top": 18.225051879882812,
        "bottom": 0.0,
        "median": 0.0,
        "trace": 18.417049407958984
      },
      "mlp": {
        "num_params": 2654208,
        "eigenvalues": [
          19.776668548583984,
          0.2724222242832184,
          6.644459288329685e-11,
          0.0,
          0.0,
          0.0,
          0.0,
          0.0,
          0.0,
          0.0,
          0.0,
          0.0,
          0.0,
          0.0,
          0.0,
          0.0,
          0.0,
          0.0,
          0.0,
          0.0
        ],
        "top": 19.776668548583984,
        "bottom": 0.0,
        "median": 0.0,
        "trace": 20.049091339111328
      }
    },
    {
      "block_idx": 10,
      "attention": {
        "num_params": 884736,
        "eigenvalues": [
          9.160408020019531,
          0.1706937849521637,
          9.039551884804098e-10,
          0.0,
          0.0,
          0.0,
          0.0,
          0.0,
          0.0,
          0.0,
          0.0,
          0.0,
          0.0,
          0.0,
          0.0,
          0.0,
          0.0,
          0.0,
          0.0,
          0.0
        ],
        "top": 9.160408020019531,
        "bottom": 0.0,
        "median": 0.0,
        "trace": 9.331101417541504
      },
      "mlp": {
        "num_params": 2654208,
        "eigenvalues": [
          15.474324226379395,
          0.15368317067623138,
          4.26140067677494e-10,
          0.0,
          0.0,
          0.0,
          0.0,
          0.0,
          0.0,
          0.0,
          0.0,
          0.0,
          0.0,
          0.0,
          0.0,
          0.0,
          0.0,
          0.0,
          0.0,
          0.0
        ],
        "top": 15.474324226379395,
        "bottom": 0.0,
        "median": 0.0,
        "trace": 15.628006935119629
      }
    },
    {
      "block_idx": 11,
      "attention": {
        "num_params": 884736,
        "eigenvalues": [
          7.292978763580322,
          0.136191725730896,
          3.021072836340011e-10,
          0.0,
          0.0,
          0.0,
          0.0,
          0.0,
          0.0,
          0.0,
          0.0,
          0.0,
          0.0,
          0.0,
          0.0,
          0.0,
          0.0,
          0.0,
          0.0,
          0.0
        ],
        "top": 7.292978763580322,
        "bottom": 0.0,
        "median": 0.0,
        "trace": 7.429170608520508
      },
      "mlp": {
        "num_params": 2654208,
        "eigenvalues": [
          403.1229553222656,
          1.7142200469970703,
          1.6165834892944986e-08,
          9.093155941945418e-18,
          0.0,
          0.0,
          0.0,
          0.0,
          0.0,
          0.0,
          0.0,
          0.0,
          0.0,
          0.0,
          0.0,
          0.0,
          0.0,
          0.0,
          0.0,
          0.0
        ],
        "top": 403.1229553222656,
        "bottom": 0.0,
        "median": 0.0,
        "trace": 404.8371887207031
      }
    },
    {
      "block_idx": 12,
      "attention": {
        "num_params": 884736,
        "eigenvalues": [
          3.5603179931640625,
          0.15822917222976685,
          2.5395216485257777e-10,
          0.0,
          0.0,
          0.0,
          0.0,
          0.0,
          0.0,
          0.0,
          0.0,
          0.0,
          0.0,
          0.0,
          0.0,
          0.0,
          0.0,
          0.0,
          0.0,
          0.0
        ],
        "top": 3.5603179931640625,
        "bottom": 0.0,
        "median": 0.0,
        "trace": 3.7185471057891846
      },
      "mlp": {
        "num_params": 2654208,
        "eigenvalues": [
          0.7911670207977295,
          0.061860162764787674,
          2.6753765869358404e-11,
          0.0,
          0.0,
          0.0,
          0.0,
          0.0,
          0.0,
          0.0,
          0.0,
          0.0,
          0.0,
          0.0,
          0.0,
          0.0,
          0.0,
          0.0,
          0.0,
          0.0
        ],
        "top": 0.7911670207977295,
        "bottom": 0.0,
        "median": 0.0,
        "trace": 0.8530271649360657
      }
    },
    {
      "block_idx": 13,
      "attention": {
        "num_params": 884736,
        "eigenvalues": [
          2.7066876888275146,
          0.18152561783790588,
          2.001500909454279e-10,
          0.0,
          0.0,
          0.0,
          0.0,
          0.0,
          0.0,
          0.0,
          0.0,
          0.0,
          0.0,
          0.0,
          0.0,
          0.0,
          0.0,
          0.0,
          0.0,
          0.0
        ],
        "top": 2.7066876888275146,
        "bottom": 0.0,
        "median": 0.0,
        "trace": 2.8882133960723877
      },
      "mlp": {
        "num_params": 2654208,
        "eigenvalues": [
          0.9068697094917297,
          0.07750662416219711,
          1.926324724732531e-11,
          0.0,
          0.0,
          0.0,
          0.0,
          0.0,
          0.0,
          0.0,
          0.0,
          0.0,
          0.0,
          0.0,
          0.0,
          0.0,
          0.0,
          0.0,
          0.0,
          0.0
        ],
        "top": 0.9068697094917297,
        "bottom": 0.0,
        "median": 0.0,
        "trace": 0.9843763113021851
      }
    },
    {
      "block_idx": 14,
      "attention": {
        "num_params": 884736,
        "eigenvalues": [
          3.37168025970459,
          0.1465529203414917,
          1.4642745349568997e-10,
          0.0,
          0.0,
          0.0,
          0.0,
          0.0,
          0.0,
          0.0,
          0.0,
          0.0,
          0.0,
          0.0,
          0.0,
          0.0,
          0.0,
          0.0,
          0.0,
          0.0
        ],
        "top": 3.37168025970459,
        "bottom": 0.0,
        "median": 0.0,
        "trace": 3.518233299255371
      },
      "mlp": {
        "num_params": 2654208,
        "eigenvalues": [
          1.0517559051513672,
          0.07240315526723862,
          3.052022523597486e-11,
          0.0,
          0.0,
          0.0,
          0.0,
          0.0,
          0.0,
          0.0,
          0.0,
          0.0,
          0.0,
          0.0,
          0.0,
          0.0,
          0.0,
          0.0,
          0.0,
          0.0
        ],
        "top": 1.0517559051513672,
        "bottom": 0.0,
        "median": 0.0,
        "trace": 1.1241590976715088
      }
    },
    {
      "block_idx": 15,
      "attention": {
        "num_params": 884736,
        "eigenvalues": [
          5.1446614265441895,
          0.17285588383674622,
          3.921762081748881e-10,
          0.0,
          0.0,
          0.0,
          0.0,
          0.0,
          0.0,
          0.0,
          0.0,
          0.0,
          0.0,
          0.0,
          0.0,
          0.0,
          0.0,
          0.0,
          0.0,
          0.0
        ],
        "top": 5.1446614265441895,
        "bottom": 0.0,
        "median": 0.0,
        "trace": 5.317517280578613
      },
      "mlp": {
        "num_params": 2654208,
        "eigenvalues": [
          1.2137070894241333,
          0.07634849101305008,
          2.165366670692226e-11,
          8.260728522766967e-17,
          0.0,
          0.0,
          0.0,
          0.0,
          0.0,
          0.0,
          0.0,
          0.0,
          0.0,
          0.0,
          0.0,
          0.0,
          0.0,
          0.0,
          0.0,
          0.0
        ],
        "top": 1.2137070894241333,
        "bottom": 0.0,
        "median": 0.0,
        "trace": 1.2900556325912476
      }
    },
    {
      "block_idx": 16,
      "attention": {
        "num_params": 884736,
        "eigenvalues": [
          4.314155101776123,
          0.19004051387310028,
          1.922316472668939e-10,
          0.0,
          0.0,
          0.0,
          0.0,
          0.0,
          0.0,
          0.0,
          0.0,
          0.0,
          0.0,
          0.0,
          0.0,
          0.0,
          0.0,
          0.0,
          0.0,
          0.0
        ],
        "top": 4.314155101776123,
        "bottom": 0.0,
        "median": 0.0,
        "trace": 4.504195690155029
      },
      "mlp": {
        "num_params": 2654208,
        "eigenvalues": [
          1.1511390209197998,
          0.06960061937570572,
          9.523696067881282e-12,
          0.0,
          0.0,
          0.0,
          0.0,
          0.0,
          0.0,
          0.0,
          0.0,
          0.0,
          0.0,
          0.0,
          0.0,
          0.0,
          0.0,
          0.0,
          0.0,
          0.0
        ],
        "top": 1.1511390209197998,
        "bottom": 0.0,
        "median": 0.0,
        "trace": 1.2207396030426025
      }
    },
    {
      "block_idx": 17,
      "attention": {
        "num_params": 884736,
        "eigenvalues": [
          5.852201461791992,
          0.1463983654975891,
          1.3567022505434068e-10,
          0.0,
          0.0,
          0.0,
          0.0,
          0.0,
          0.0,
          0.0,
          0.0,
          0.0,
          0.0,
          0.0,
          0.0,
          0.0,
          0.0,
          0.0,
          0.0,
          0.0
        ],
        "top": 5.852201461791992,
        "bottom": 0.0,
        "median": 0.0,
        "trace": 5.998600006103516
      },
      "mlp": {
        "num_params": 2654208,
        "eigenvalues": [
          1.3171933889389038,
          0.07241817563772202,
          5.076673109671859e-11,
          0.0,
          0.0,
          0.0,
          0.0,
          0.0,
          0.0,
          0.0,
          0.0,
          0.0,
          0.0,
          0.0,
          0.0,
          0.0,
          0.0,
          0.0,
          0.0,
          0.0
        ],
        "top": 1.3171933889389038,
        "bottom": 0.0,
        "median": 0.0,
        "trace": 1.3896116018295288
      }
    },
    {
      "block_idx": 18,
      "attention": {
        "num_params": 884736,
        "eigenvalues": [
          3.3371286392211914,
          0.13368727266788483,
          5.838397820756569e-11,
          8.506756025178001e-18,
          0.0,
          0.0,
          0.0,
          0.0,
          0.0,
          0.0,
          0.0,
          0.0,
          0.0,
          0.0,
          0.0,
          0.0,
          0.0,
          0.0,
          0.0,
          0.0
        ],
        "top": 3.3371286392211914,
        "bottom": 0.0,
        "median": 0.0,
        "trace": 3.470815896987915
      },
      "mlp": {
        "num_params": 2654208,
        "eigenvalues": [
          2.1544861793518066,
          0.12936142086982727,
          5.5502036994115045e-11,
          0.0,
          0.0,
          0.0,
          0.0,
          0.0,
          0.0,
          0.0,
          0.0,
          0.0,
          0.0,
          0.0,
          0.0,
          0.0,
          0.0,
          0.0,
          0.0,
          0.0
        ],
        "top": 2.1544861793518066,
        "bottom": 0.0,
        "median": 0.0,
        "trace": 2.2838475704193115
      }
    },
    {
      "block_idx": 19,
      "attention": {
        "num_params": 884736,
        "eigenvalues": [
          14.446542739868164,
          0.302418977022171,
          1.69133884675432e-09,
          1.7031123552777869e-18,
          0.0,
          0.0,
          0.0,
          0.0,
          0.0,
          0.0,
          0.0,
          0.0,
          0.0,
          0.0,
          0.0,
          0.0,
          0.0,
          0.0,
          0.0,
          0.0
        ],
        "top": 14.446542739868164,
        "bottom": 0.0,
        "median": 0.0,
        "trace": 14.748961448669434
      },
      "mlp": {
        "num_params": 2654208,
        "eigenvalues": [
          1.8345049619674683,
          0.09476077556610107,
          1.2877780786180182e-10,
          1.3297042084124146e-18,
          0.0,
          0.0,
          0.0,
          0.0,
          0.0,
          0.0,
          0.0,
          0.0,
          0.0,
          0.0,
          0.0,
          0.0,
          0.0,
          0.0,
          0.0,
          0.0
        ],
        "top": 1.8345049619674683,
        "bottom": 0.0,
        "median": 0.0,
        "trace": 1.9292657375335693
      }
    },
    {
      "block_idx": 20,
      "attention": {
        "num_params": 884736,
        "eigenvalues": [
          1.687314510345459,
          0.04490407928824425,
          9.437779030507798e-11,
          0.0,
          0.0,
          0.0,
          0.0,
          0.0,
          0.0,
          0.0,
          0.0,
          0.0,
          0.0,
          0.0,
          0.0,
          0.0,
          0.0,
          0.0,
          0.0,
          0.0
        ],
        "top": 1.687314510345459,
        "bottom": 0.0,
        "median": 0.0,
        "trace": 1.732218623161316
      },
      "mlp": {
        "num_params": 2654208,
        "eigenvalues": [
          2.6212849617004395,
          0.13061995804309845,
          1.4882671484084398e-11,
          0.0,
          0.0,
          0.0,
          0.0,
          0.0,
          0.0,
          0.0,
          0.0,
          0.0,
          0.0,
          0.0,
          0.0,
          0.0,
          0.0,
          0.0,
          0.0,
          0.0
        ],
        "top": 2.6212849617004395,
        "bottom": 0.0,
        "median": 0.0,
        "trace": 2.7519049644470215
      }
    },
    {
      "block_idx": 21,
      "attention": {
        "num_params": 884736,
        "eigenvalues": [
          3.6383330821990967,
          0.1401561051607132,
          1.9017308561242174e-10,
          0.0,
          0.0,
          0.0,
          0.0,
          0.0,
          0.0,
          0.0,
          0.0,
          0.0,
          0.0,
          0.0,
          0.0,
          0.0,
          0.0,
          0.0,
          0.0,
          0.0
        ],
        "top": 3.6383330821990967,
        "bottom": 0.0,
        "median": 0.0,
        "trace": 3.778489112854004
      },
      "mlp": {
        "num_params": 2654208,
        "eigenvalues": [
          1.2988560199737549,
          0.07178311049938202,
          4.507648768137251e-11,
          0.0,
          0.0,
          0.0,
          0.0,
          0.0,
          0.0,
          0.0,
          0.0,
          0.0,
          0.0,
          0.0,
          0.0,
          0.0,
          0.0,
          0.0,
          0.0,
          0.0
        ],
        "top": 1.2988560199737549,
        "bottom": 0.0,
        "median": 0.0,
        "trace": 1.3706390857696533
      }
    },
    {
      "block_idx": 22,
      "attention": {
        "num_params": 884736,
        "eigenvalues": [
          3.0744848251342773,
          0.08304744213819504,
          1.8107230992381318e-10,
          0.0,
          0.0,
          0.0,
          0.0,
          0.0,
          0.0,
          0.0,
          0.0,
          0.0,
          0.0,
          0.0,
          0.0,
          0.0,
          0.0,
          0.0,
          0.0,
          0.0
        ],
        "top": 3.0744848251342773,
        "bottom": 0.0,
        "median": 0.0,
        "trace": 3.157532215118408
      },
      "mlp": {
        "num_params": 2654208,
        "eigenvalues": [
          1.8657488822937012,
          0.10686320811510086,
          2.891932179838186e-11,
          0.0,
          0.0,
          0.0,
          0.0,
          0.0,
          0.0,
          0.0,
          0.0,
          0.0,
          0.0,
          0.0,
          0.0,
          0.0,
          0.0,
          0.0,
          0.0,
          0.0
        ],
        "top": 1.8657488822937012,
        "bottom": 0.0,
        "median": 0.0,
        "trace": 1.9726121425628662
      }
    },
    {
      "block_idx": 23,
      "attention": {
        "num_params": 884736,
        "eigenvalues": [
          2.0998358726501465,
          0.17056572437286377,
          2.0070142769945676e-10,
          0.0,
          0.0,
          0.0,
          0.0,
          0.0,
          0.0,
          0.0,
          0.0,
          0.0,
          0.0,
          0.0,
          0.0,
          0.0,
          0.0,
          0.0,
          0.0,
          0.0
        ],
        "top": 2.0998358726501465,
        "bottom": 0.0,
        "median": 0.0,
        "trace": 2.2704014778137207
      },
      "mlp": {
        "num_params": 2654208,
        "eigenvalues": [
          1.3810306787490845,
          0.08544363081455231,
          6.086935122606718e-11,
          0.0,
          0.0,
          0.0,
          0.0,
          0.0,
          0.0,
          0.0,
          0.0,
          0.0,
          0.0,
          0.0,
          0.0,
          0.0,
          0.0,
          0.0,
          0.0,
          0.0
        ],
        "top": 1.3810306787490845,
        "bottom": 0.0,
        "median": 0.0,
        "trace": 1.4664742946624756
      }
    },
    {
      "block_idx": 24,
      "attention": {
        "num_params": 884736,
        "eigenvalues": [
          4.28722620010376,
          0.11102057248353958,
          3.11005193820435e-10,
          0.0,
          0.0,
          0.0,
          0.0,
          0.0,
          0.0,
          0.0,
          0.0,
          0.0,
          0.0,
          0.0,
          0.0,
          0.0,
          0.0,
          0.0,
          0.0,
          0.0
        ],
        "top": 4.28722620010376,
        "bottom": 0.0,
        "median": 0.0,
        "trace": 4.398246765136719
      },
      "mlp": {
        "num_params": 2654208,
        "eigenvalues": [
          0.8752383589744568,
          0.07379874587059021,
          7.235712723430154e-11,
          0.0,
          0.0,
          0.0,
          0.0,
          0.0,
          0.0,
          0.0,
          0.0,
          0.0,
          0.0,
          0.0,
          0.0,
          0.0,
          0.0,
          0.0,
          0.0,
          0.0
        ],
        "top": 0.8752383589744568,
        "bottom": 0.0,
        "median": 0.0,
        "trace": 0.9490370750427246
      }
    },
    {
      "block_idx": 25,
      "attention": {
        "num_params": 884736,
        "eigenvalues": [
          2.306168556213379,
          0.05987093970179558,
          7.4447656372989e-11,
          0.0,
          0.0,
          0.0,
          0.0,
          0.0,
          0.0,
          0.0,
          0.0,
          0.0,
          0.0,
          0.0,
          0.0,
          0.0,
          0.0,
          0.0,
          0.0,
          0.0
        ],
        "top": 2.306168556213379,
        "bottom": 0.0,
        "median": 0.0,
        "trace": 2.366039514541626
      },
      "mlp": {
        "num_params": 2654208,
        "eigenvalues": [
          0.9579044580459595,
          0.06694392114877701,
          1.208872672103789e-11,
          0.0,
          0.0,
          0.0,
          0.0,
          0.0,
          0.0,
          0.0,
          0.0,
          0.0,
          0.0,
          0.0,
          0.0,
          0.0,
          0.0,
          0.0,
          0.0,
          0.0
        ],
        "top": 0.9579044580459595,
        "bottom": 0.0,
        "median": 0.0,
        "trace": 1.0248483419418335
      }
    },
    {
      "block_idx": 26,
      "attention": {
        "num_params": 884736,
        "eigenvalues": [
          1.146213173866272,
          0.058524541556835175,
          1.270989979929027e-10,
          0.0,
          0.0,
          0.0,
          0.0,
          0.0,
          0.0,
          0.0,
          0.0,
          0.0,
          0.0,
          0.0,
          0.0,
          0.0,
          0.0,
          0.0,
          0.0,
          0.0
        ],
        "top": 1.146213173866272,
        "bottom": 0.0,
        "median": 0.0,
        "trace": 1.204737663269043
      },
      "mlp": {
        "num_params": 2654208,
        "eigenvalues": [
          1.7972418069839478,
          0.11278535425662994,
          1.0420529716892446e-10,
          0.0,
          0.0,
          0.0,
          0.0,
          0.0,
          0.0,
          0.0,
          0.0,
          0.0,
          0.0,
          0.0,
          0.0,
          0.0,
          0.0,
          0.0,
          0.0,
          0.0
        ],
        "top": 1.7972418069839478,
        "bottom": 0.0,
        "median": 0.0,
        "trace": 1.9100271463394165
      }
    },
    {
      "block_idx": 27,
      "attention": {
        "num_params": 884736,
        "eigenvalues": [
          20.26531982421875,
          0.1822730451822281,
          4.526032326701568e-10,
          0.0,
          0.0,
          0.0,
          0.0,
          0.0,
          0.0,
          0.0,
          0.0,
          0.0,
          0.0,
          0.0,
          0.0,
          0.0,
          0.0,
          0.0,
          0.0,
          0.0
        ],
        "top": 20.26531982421875,
        "bottom": 0.0,
        "median": 0.0,
        "trace": 20.447593688964844
      },
      "mlp": {
        "num_params": 2654208,
        "eigenvalues": [
          1.7710977792739868,
          0.09373527765274048,
          4.475926920766149e-11,
          0.0,
          0.0,
          0.0,
          0.0,
          0.0,
          0.0,
          0.0,
          0.0,
          0.0,
          0.0,
          0.0,
          0.0,
          0.0,
          0.0,
          0.0,
          0.0,
          0.0
        ],
        "top": 1.7710977792739868,
        "bottom": 0.0,
        "median": 0.0,
        "trace": 1.864833116531372
      }
    },
    {
      "block_idx": 28,
      "attention": {
        "num_params": 884736,
        "eigenvalues": [
          1.7399165630340576,
          0.05753468722105026,
          1.195749887994424e-10,
          0.0,
          0.0,
          0.0,
          0.0,
          0.0,
          0.0,
          0.0,
          0.0,
          0.0,
          0.0,
          0.0,
          0.0,
          0.0,
          0.0,
          0.0,
          0.0,
          0.0
        ],
        "top": 1.7399165630340576,
        "bottom": 0.0,
        "median": 0.0,
        "trace": 1.7974512577056885
      },
      "mlp": {
        "num_params": 2654208,
        "eigenvalues": [
          378.0593566894531,
          0.4827401638031006,
          1.5271501840885549e-09,
          0.0,
          0.0,
          0.0,
          0.0,
          0.0,
          0.0,
          0.0,
          0.0,
          0.0,
          0.0,
          0.0,
          0.0,
          0.0,
          0.0,
          0.0,
          0.0,
          0.0
        ],
        "top": 378.0593566894531,
        "bottom": 0.0,
        "median": 0.0,
        "trace": 378.5420837402344
      }
    },
    {
      "block_idx": 29,
      "attention": {
        "num_params": 884736,
        "eigenvalues": [
          1.2159472703933716,
          0.05276856943964958,
          4.5356021022291415e-11,
          0.0,
          0.0,
          0.0,
          0.0,
          0.0,
          0.0,
          0.0,
          0.0,
          0.0,
          0.0,
          0.0,
          0.0,
          0.0,
          0.0,
          0.0,
          0.0,
          0.0
        ],
        "top": 1.2159472703933716,
        "bottom": 0.0,
        "median": 0.0,
        "trace": 1.2687158584594727
      },
      "mlp": {
        "num_params": 2654208,
        "eigenvalues": [
          145.38760375976562,
          0.7798980474472046,
          6.8097874006411985e-09,
          0.0,
          0.0,
          0.0,
          0.0,
          0.0,
          0.0,
          0.0,
          0.0,
          0.0,
          0.0,
          0.0,
          0.0,
          0.0,
          0.0,
          0.0,
          0.0,
          0.0
        ],
        "top": 145.38760375976562,
        "bottom": 0.0,
        "median": 0.0,
        "trace": 146.16749572753906
      }
    }
  ],
  "output": {
    "num_params": 28311552,
    "eigenvalues": [
      29.531864166259766,
      2.7143356800079346,
      1.2608453170415146e-10,
      0.0,
      0.0,
      0.0,
      0.0,
      0.0,
      0.0,
      0.0,
      0.0,
      0.0,
      0.0,
      0.0,
      0.0,
      0.0,
      0.0,
      0.0,
      0.0,
      0.0
    ],
    "top": 29.531864166259766,
    "bottom": 0.0,
    "median": 0.0,
    "trace": 32.24620056152344
  }
}