{
  "architecture": "phi",
  "num_blocks": 24,
  "blocks": [
    {
      "block_idx": 0,
      "attention": {
        "num_params": 16785408,
        "eigenvalues": [
          4.5929670333862305,
          0.5772252082824707,
          0.4093211889266968,
          0.35354024171829224,
          0.3188084661960602,
          4.4288520073543225e-10,
          0.0,
          0.0,
          0.0,
          0.0,
          0.0,
          0.0,
          0.0,
          0.0,
          0.0,
          0.0,
          0.0,
          0.0,
          0.0,
          0.0
        ],
        "top": 4.5929670333862305,
        "bottom": 0.0,
        "median": 0.0,
        "trace": 6.251862049102783
      },
      "mlp": {
        "num_params": 33564672,
        "eigenvalues": [
          0.5790808200836182,
          0.16917046904563904,
          0.1404358595609665,
          0.1165856420993805,
          0.10555471479892731,
          8.252848057721529e-12,
          0.0,
          0.0,
          0.0,
          0.0,
          0.0,
          0.0,
          0.0,
          0.0,
          0.0,
          0.0,
          0.0,
          0.0,
          0.0,
          0.0
        ],
        "top": 0.5790808200836182,
        "bottom": 0.0,
        "median": 0.0,
        "trace": 1.1108275651931763
      }
    },
    {
      "block_idx": 1,
      "attention": {
        "num_params": 16785408,
        "eigenvalues": [
          2.6364996433258057,
          0.34301477670669556,
          0.2297399640083313,
          0.20645609498023987,
          0.17607168853282928,
          7.557836301241849e-11,
          0.0,
          0.0,
          0.0,
          0.0,
          0.0,
          0.0,
          0.0,
          0.0,
          0.0,
          0.0,
          0.0,
          0.0,
          0.0,
          0.0
        ],
        "top": 2.6364996433258057,
        "bottom": 0.0,
        "median": 0.0,
        "trace": 3.5917820930480957
      },
      "mlp": {
        "num_params": 33564672,
        "eigenvalues": [
          2.0155553817749023,
          0.21591363847255707,
          0.17991560697555542,
          0.14090222120285034,
          0.1372203230857849,
          2.8677452773573364e-11,
          1.6392961088644272e-15,
          0.0,
          0.0,
          0.0,
          0.0,
          0.0,
          0.0,
          0.0,
          0.0,
          0.0,
          0.0,
          0.0,
          0.0,
          0.0
        ],
        "top": 2.0155553817749023,
        "bottom": 0.0,
        "median": 0.0,
        "trace": 2.689507007598877
      }
    },
    {
      "block_idx": 2,
      "attention": {
        "num_params": 16785408,
        "eigenvalues": [
          1.8931593894958496,
          0.28598105907440186,
          0.19597046077251434,
          0.1722884625196457,
          0.14841893315315247,
          3.118991176442876e-11,
          3.0919992768386453e-16,
          0.0,
          0.0,
          0.0,
          0.0,
          0.0,
          0.0,
          0.0,
          0.0,
          0.0,
          0.0,
          0.0,
          0.0,
          0.0
        ],
        "top": 1.8931593894958496,
        "bottom": 0.0,
        "median": 0.0,
        "trace": 2.6958184242248535
      },
      "mlp": {
        "num_params": 33564672,
        "eigenvalues": [
          1.7399154901504517,
          0.2320115566253662,
          0.17401625216007233,
          0.14631213247776031,
          0.13730578124523163,
          3.462978515056392e-11,
          1.056082055065201e-15,
          0.0,
          0.0,
          0.0,
          0.0,
          0.0,
          0.0,
          0.0,
          0.0,
          0.0,
          0.0,
          0.0,
          0.0,
          0.0
        ],
        "top": 1.7399154901504517,
        "bottom": 0.0,
        "median": 0.0,
        "trace": 2.429561138153076
      }
    },
    {
      "block_idx": 3,
      "attention": {
        "num_params": 16785408,
        "eigenvalues": [
          4.8296217918396,
          0.5831565856933594,
          0.3187442123889923,
          0.2641048729419708,
          0.23059020936489105,
          8.474109608469504e-11,
          1.0127291353494925e-16,
          0.0,
          0.0,
          0.0,
          0.0,
          0.0,
          0.0,
          0.0,
          0.0,
          0.0,
          0.0,
          0.0,
          0.0,
          0.0
        ],
        "top": 4.8296217918396,
        "bottom": 0.0,
        "median": 0.0,
        "trace": 6.226217746734619
      },
      "mlp": {
        "num_params": 33564672,
        "eigenvalues": [
          1.6843101978302002,
          0.2776501476764679,
          0.21454764902591705,
          0.18543079495429993,
          0.16831636428833008,
          2.2783806091775105e-11,
          2.1452308470231113e-16,
          0.0,
          0.0,
          0.0,
          0.0,
          0.0,
          0.0,
          0.0,
          0.0,
          0.0,
          0.0,
          0.0,
          0.0,
          0.0
        ],
        "top": 1.6843101978302002,
        "bottom": 0.0,
        "median": 0.0,
        "trace": 2.530255079269409
      }
    },
    {
      "block_idx": 4,
      "attention": {
        "num_params": 16785408,
        "eigenvalues": [
          3.116008996963501,
          0.3907102346420288,
          0.22141152620315552,
          0.19837166368961334,
          0.17626453936100006,
          7.343053248787257e-11,
          1.0252515380928021e-15,
          0.0,
          0.0,
          0.0,
          0.0,
          0.0,
          0.0,
          0.0,
          0.0,
          0.0,
          0.0,
          0.0,
          0.0,
          0.0
        ],
        "top": 3.116008996963501,
        "bottom": 0.0,
        "median": 0.0,
        "trace": 4.102766990661621
      },
      "mlp": {
        "num_params": 33564672,
        "eigenvalues": [
          2.143028736114502,
          0.36162838339805603,
          0.2821492552757263,
          0.24207206070423126,
          0.2173699587583542,
          4.3894145262957096e-11,
          0.0,
          0.0,
          0.0,
          0.0,
          0.0,
          0.0,
          0.0,
          0.0,
          0.0,
          0.0,
          0.0,
          0.0,
          0.0,
          0.0
        ],
        "top": 2.143028736114502,
        "bottom": 0.0,
        "median": 0.0,
        "trace": 3.246248245239258
      }
    },
    {
      "block_idx": 5,
      "attention": {
        "num_params": 16785408,
        "eigenvalues": [
          3.494436740875244,
          0.38853031396865845,
          0.20146264135837555,
          0.18766650557518005,
          0.1667703092098236,
          1.3042977808908063e-10,
          0.0,
          0.0,
          0.0,
          0.0,
          0.0,
          0.0,
          0.0,
          0.0,
          0.0,
          0.0,
          0.0,
          0.0,
          0.0,
          0.0
        ],
        "top": 3.494436740875244,
        "bottom": 0.0,
        "median": 0.0,
        "trace": 4.43886661529541
      },
      "mlp": {
        "num_params": 33564672,
        "eigenvalues": [
          2.471095085144043,
          0.38312262296676636,
          0.3027155101299286,
          0.26292145252227783,
          0.22831274569034576,
          4.086025268135174e-11,
          0.0,
          0.0,
          0.0,
          0.0,
          0.0,
          0.0,
          0.0,
          0.0,
          0.0,
          0.0,
          0.0,
          0.0,
          0.0,
          0.0
        ],
        "top": 2.471095085144043,
        "bottom": 0.0,
        "median": 0.0,
        "trace": 3.648167371749878
      }
    },
    {
      "block_idx": 6,
      "attention": {
        "num_params": 16785408,
        "eigenvalues": [
          5.731625080108643,
          0.36026135087013245,
          0.22799059748649597,
          0.221440851688385,
          0.18399553000926971,
          5.5796978148947574e-11,
          8.777553404709822e-15,
          0.0,
          0.0,
          0.0,
          0.0,
          0.0,
          0.0,
          0.0,
          0.0,
          0.0,
          0.0,
          0.0,
          0.0,
          0.0
        ],
        "top": 5.731625080108643,
        "bottom": 0.0,
        "median": 0.0,
        "trace": 6.725313663482666
      },
      "mlp": {
        "num_params": 33564672,
        "eigenvalues": [
          2.6987099647521973,
          0.3705662488937378,
          0.3118322789669037,
          0.27505117654800415,
          0.23458757996559143,
          3.6017015758726956e-11,
          4.603225433446321e-16,
          0.0,
          0.0,
          0.0,
          0.0,
          0.0,
          0.0,
          0.0,
          0.0,
          0.0,
          0.0,
          0.0,
          0.0,
          0.0
        ],
        "top": 2.6987099647521973,
        "bottom": 0.0,
        "median": 0.0,
        "trace": 3.890747547149658
      }
    },
    {
      "block_idx": 7,
      "attention": {
        "num_params": 16785408,
        "eigenvalues": [
          4.650832176208496,
          0.30871838331222534,
          0.20116226375102997,
          0.1900908499956131,
          0.16324305534362793,
          1.6995410634379482e-10,
          0.0,
          0.0,
          0.0,
          0.0,
          0.0,
          0.0,
          0.0,
          0.0,
          0.0,
          0.0,
          0.0,
          0.0,
          0.0,
          0.0
        ],
        "top": 4.650832176208496,
        "bottom": 0.0,
        "median": 0.0,
        "trace": 5.514046669006348
      },
      "mlp": {
        "num_params": 33564672,
        "eigenvalues": [
          2.8100030422210693,
          0.35452306270599365,
          0.29432106018066406,
          0.26527607440948486,
          0.2306932955980301,
          6.049886286385586e-11,
          0.0,
          0.0,
          0.0,
          0.0,
          0.0,
          0.0,
          0.0,
          0.0,
          0.0,
          0.0,
          0.0,
          0.0,
          0.0,
          0.0
        ],
        "top": 2.8100030422210693,
        "bottom": 0.0,
        "median": 0.0,
        "trace": 3.9548163414001465
      }
    },
    {
      "block_idx": 8,
      "attention": {
        "num_params": 16785408,
        "eigenvalues": [
          5.0293426513671875,
          0.26603439450263977,
          0.19869369268417358,
          0.18521055579185486,
          0.15336839854717255,
          1.1507409608535468e-10,
          3.887715209439577e-15,
          0.0,
          0.0,
          0.0,
          0.0,
          0.0,
          0.0,
          0.0,
          0.0,
          0.0,
          0.0,
          0.0,
          0.0,
          0.0
        ],
        "top": 5.0293426513671875,
        "bottom": 0.0,
        "median": 0.0,
        "trace": 5.832650184631348
      },
      "mlp": {
        "num_params": 33564672,
        "eigenvalues": [
          3.3158717155456543,
          0.3460296094417572,
          0.30848515033721924,
          0.27873876690864563,
          0.2315904200077057,
          5.051143531220603e-11,
          0.0,
          0.0,
          0.0,
          0.0,
          0.0,
          0.0,
          0.0,
          0.0,
          0.0,
          0.0,
          0.0,
          0.0,
          0.0,
          0.0
        ],
        "top": 3.3158717155456543,
        "bottom": 0.0,
        "median": 0.0,
        "trace": 4.480715274810791
      }
    },
    {
      "block_idx": 9,
      "attention": {
        "num_params": 16785408,
        "eigenvalues": [
          4.028717041015625,
          0.2567632794380188,
          0.20061178505420685,
          0.19423438608646393,
          0.15271708369255066,
          1.274859662281358e-10,
          4.6959177946994876e-14,
          0.0,
          0.0,
          0.0,
          0.0,
          0.0,
          0.0,
          0.0,
          0.0,
          0.0,
          0.0,
          0.0,
          0.0,
          0.0
        ],
        "top": 4.028717041015625,
        "bottom": 0.0,
        "median": 0.0,
        "trace": 4.833043575286865
      },
      "mlp": {
        "num_params": 33564672,
        "eigenvalues": [
          3.133732795715332,
          0.3243105113506317,
          0.28795719146728516,
          0.25527438521385193,
          0.20653142035007477,
          2.954874192551138e-11,
          7.290233853065892e-15,
          0.0,
          0.0,
          0.0,
          0.0,
          0.0,
          0.0,
          0.0,
          0.0,
          0.0,
          0.0,
          0.0,
          0.0,
          0.0
        ],
        "top": 3.133732795715332,
        "bottom": 0.0,
        "median": 0.0,
        "trace": 4.207806587219238
      }
    },
    {
      "block_idx": 10,
      "attention": {
        "num_params": 16785408,
        "eigenvalues": [
          7.872888565063477,
          0.31536269187927246,
          0.21607229113578796,
          0.19774100184440613,
          0.1583424210548401,
          2.5666699321469366e-10,
          7.154174103715487e-15,
          0.0,
          0.0,
          0.0,
          0.0,
          0.0,
          0.0,
          0.0,
          0.0,
          0.0,
          0.0,
          0.0,
          0.0,
          0.0
        ],
        "top": 7.872888565063477,
        "bottom": 0.0,
        "median": 0.0,
        "trace": 8.760407447814941
      },
      "mlp": {
        "num_params": 33564672,
        "eigenvalues": [
          3.486679792404175,
          0.304169237613678,
          0.2772747278213501,
          0.26113462448120117,
          0.20733897387981415,
          1.305437286047706e-10,
          1.5254272251277214e-14,
          0.0,
          0.0,
          0.0,
          0.0,
          0.0,
          0.0,
          0.0,
          0.0,
          0.0,
          0.0,
          0.0,
          0.0,
          0.0
        ],
        "top": 3.486679792404175,
        "bottom": 0.0,
        "median": 0.0,
        "trace": 4.53659725189209
      }
    },
    {
      "block_idx": 11,
      "attention": {
        "num_params": 16785408,
        "eigenvalues": [
          12.301542282104492,
          0.4061201512813568,
          0.3305138051509857,
          0.2745635509490967,
          0.2152894139289856,
          1.7672249774669524e-10,
          0.0,
          0.0,
          0.0,
          0.0,
          0.0,
          0.0,
          0.0,
          0.0,
          0.0,
          0.0,
          0.0,
          0.0,
          0.0,
          0.0
        ],
        "top": 12.301542282104492,
        "bottom": 0.0,
        "median": 0.0,
        "trace": 13.528029441833496
      },
      "mlp": {
        "num_params": 33564672,
        "eigenvalues": [
          4.099656581878662,
          0.291843980550766,
          0.2737935483455658,
          0.24671940505504608,
          0.21710923314094543,
          3.973815027036309e-11,
          1.8232125844599902e-15,
          0.0,
          0.0,
          0.0,
          0.0,
          0.0,
          0.0,
          0.0,
          0.0,
          0.0,
          0.0,
          0.0,
          0.0,
          0.0
        ],
        "top": 4.099656581878662,
        "bottom": 0.0,
        "median": 0.0,
        "trace": 5.129122734069824
      }
    },
    {
      "block_idx": 12,
      "attention": {
        "num_params": 16785408,
        "eigenvalues": [
          8.596051216125488,
          0.23336544632911682,
          0.20647019147872925,
          0.18079660832881927,
          0.14863631129264832,
          2.3628976553169423e-10,
          7.011215271009695e-15,
          0.0,
          0.0,
          0.0,
          0.0,
          0.0,
          0.0,
          0.0,
          0.0,
          0.0,
          0.0,
          0.0,
          0.0,
          0.0
        ],
        "top": 8.596051216125488,
        "bottom": 0.0,
        "median": 0.0,
        "trace": 9.36531925201416
      },
      "mlp": {
        "num_params": 33564672,
        "eigenvalues": [
          3.758362054824829,
          0.26038017868995667,
          0.25574934482574463,
          0.22667919099330902,
          0.20515850186347961,
          1.872967198002229e-10,
          8.534493912363411e-15,
          0.0,
          0.0,
          0.0,
          0.0,
          0.0,
          0.0,
          0.0,
          0.0,
          0.0,
          0.0,
          0.0,
          0.0,
          0.0
        ],
        "top": 3.758362054824829,
        "bottom": 0.0,
        "median": 0.0,
        "trace": 4.706329345703125
      }
    },
    {
      "block_idx": 13,
      "attention": {
        "num_params": 16785408,
        "eigenvalues": [
          8.040803909301758,
          0.23883605003356934,
          0.22389186918735504,
          0.19199170172214508,
          0.17010995745658875,
          2.2077348837967747e-09,
          0.0,
          0.0,
          0.0,
          0.0,
          0.0,
          0.0,
          0.0,
          0.0,
          0.0,
          0.0,
          0.0,
          0.0,
          0.0,
          0.0
        ],
        "top": 8.040803909301758,
        "bottom": 0.0,
        "median": 0.0,
        "trace": 8.865633964538574
      },
      "mlp": {
        "num_params": 33564672,
        "eigenvalues": [
          3.2358434200286865,
          0.2557738423347473,
          0.2489778846502304,
          0.22416052222251892,
          0.19998358190059662,
          6.230596594214433e-10,
          0.0,
          0.0,
          0.0,
          0.0,
          0.0,
          0.0,
          0.0,
          0.0,
          0.0,
          0.0,
          0.0,
          0.0,
          0.0,
          0.0
        ],
        "top": 3.2358434200286865,
        "bottom": 0.0,
        "median": 0.0,
        "trace": 4.16473913192749
      }
    },
    {
      "block_idx": 14,
      "attention": {
        "num_params": 16785408,
        "eigenvalues": [
          8.423426628112793,
          0.22175118327140808,
          0.20834881067276,
          0.18059535324573517,
          0.15403422713279724,
          1.6106928291126366e-10,
          8.596676612724599e-16,
          0.0,
          0.0,
          0.0,
          0.0,
          0.0,
          0.0,
          0.0,
          0.0,
          0.0,
          0.0,
          0.0,
          0.0,
          0.0
        ],
        "top": 8.423426628112793,
        "bottom": 0.0,
        "median": 0.0,
        "trace": 9.188157081604004
      },
      "mlp": {
        "num_params": 33564672,
        "eigenvalues": [
          3.5343847274780273,
          0.26483064889907837,
          0.25111648440361023,
          0.22701604664325714,
          0.20588620007038116,
          2.7255020462746415e-10,
          0.0,
          0.0,
          0.0,
          0.0,
          0.0,
          0.0,
          0.0,
          0.0,
          0.0,
          0.0,
          0.0,
          0.0,
          0.0,
          0.0
        ],
        "top": 3.5343847274780273,
        "bottom": 0.0,
        "median": 0.0,
        "trace": 4.483234405517578
      }
    },
    {
      "block_idx": 15,
      "attention": {
        "num_params": 16785408,
        "eigenvalues": [
          13.376846313476562,
          0.2734333872795105,
          0.23561087250709534,
          0.21213114261627197,
          0.1835366040468216,
          3.6521002888534326e-10,
          0.0,
          0.0,
          0.0,
          0.0,
          0.0,
          0.0,
          0.0,
          0.0,
          0.0,
          0.0,
          0.0,
          0.0,
          0.0,
          0.0
        ],
        "top": 13.376846313476562,
        "bottom": 0.0,
        "median": 0.0,
        "trace": 14.281558990478516
      },
      "mlp": {
        "num_params": 33564672,
        "eigenvalues": [
          3.663334846496582,
          0.2717996835708618,
          0.25422459840774536,
          0.24092935025691986,
          0.21166720986366272,
          5.00371022393864e-10,
          7.509085990812722e-15,
          0.0,
          0.0,
          0.0,
          0.0,
          0.0,
          0.0,
          0.0,
          0.0,
          0.0,
          0.0,
          0.0,
          0.0,
          0.0
        ],
        "top": 3.663334846496582,
        "bottom": 0.0,
        "median": 0.0,
        "trace": 4.641955375671387
      }
    },
    {
      "block_idx": 16,
      "attention": {
        "num_params": 16785408,
        "eigenvalues": [
          10.557788848876953,
          0.26985734701156616,
          0.23871654272079468,
          0.20687025785446167,
          0.1839742511510849,
          3.002274817642814e-10,
          4.943962245347079e-14,
          0.0,
          0.0,
          0.0,
          0.0,
          0.0,
          0.0,
          0.0,
          0.0,
          0.0,
          0.0,
          0.0,
          0.0,
          0.0
        ],
        "top": 10.557788848876953,
        "bottom": 0.0,
        "median": 0.0,
        "trace": 11.457207679748535
      },
      "mlp": {
        "num_params": 33564672,
        "eigenvalues": [
          3.4557859897613525,
          0.2687271535396576,
          0.2487449049949646,
          0.23445264995098114,
          0.20671817660331726,
          2.202763110803474e-10,
          6.116558319812495e-15,
          0.0,
          0.0,
          0.0,
          0.0,
          0.0,
          0.0,
          0.0,
          0.0,
          0.0,
          0.0,
          0.0,
          0.0,
          0.0
        ],
        "top": 3.4557859897613525,
        "bottom": 0.0,
        "median": 0.0,
        "trace": 4.4144287109375
      }
    },
    {
      "block_idx": 17,
      "attention": {
        "num_params": 16785408,
        "eigenvalues": [
          9.000704765319824,
          0.2154419720172882,
          0.19531916081905365,
          0.18108472228050232,
          0.14180773496627808,
          8.221405500830059e-11,
          9.609465119789738e-15,
          0.0,
          0.0,
          0.0,
          0.0,
          0.0,
          0.0,
          0.0,
          0.0,
          0.0,
          0.0,
          0.0,
          0.0,
          0.0
        ],
        "top": 9.000704765319824,
        "bottom": 0.0,
        "median": 0.0,
        "trace": 9.734357833862305
      },
      "mlp": {
        "num_params": 33564672,
        "eigenvalues": [
          3.5855650901794434,
          0.2825923264026642,
          0.2505415081977844,
          0.23681432008743286,
          0.20599158108234406,
          2.311671076782318e-09,
          1.4673341268908193e-15,
          0.0,
          0.0,
          0.0,
          0.0,
          0.0,
          0.0,
          0.0,
          0.0,
          0.0,
          0.0,
          0.0,
          0.0,
          0.0
        ],
        "top": 3.5855650901794434,
        "bottom": 0.0,
        "median": 0.0,
        "trace": 4.56150484085083
      }
    },
    {
      "block_idx": 18,
      "attention": {
        "num_params": 16785408,
        "eigenvalues": [
          13.535244941711426,
          0.49687162041664124,
          0.33535802364349365,
          0.3151620626449585,
          0.25059571862220764,
          3.3600391913246597e-10,
          0.0,
          0.0,
          0.0,
          0.0,
          0.0,
          0.0,
          0.0,
          0.0,
          0.0,
          0.0,
          0.0,
          0.0,
          0.0,
          0.0
        ],
        "top": 13.535244941711426,
        "bottom": 0.0,
        "median": 0.0,
        "trace": 14.933233261108398
      },
      "mlp": {
        "num_params": 33564672,
        "eigenvalues": [
          4.717259407043457,
          0.2670043706893921,
          0.2398412823677063,
          0.23355738818645477,
          0.2009352594614029,
          1.403996779947292e-10,
          0.0,
          0.0,
          0.0,
          0.0,
          0.0,
          0.0,
          0.0,
          0.0,
          0.0,
          0.0,
          0.0,
          0.0,
          0.0,
          0.0
        ],
        "top": 4.717259407043457,
        "bottom": 0.0,
        "median": 0.0,
        "trace": 5.658597946166992
      }
    },
    {
      "block_idx": 19,
      "attention": {
        "num_params": 16785408,
        "eigenvalues": [
          10.630175590515137,
          0.25879281759262085,
          0.19153638184070587,
          0.16529476642608643,
          0.14977392554283142,
          5.353574805688766e-10,
          7.611701660680328e-14,
          0.0,
          0.0,
          0.0,
          0.0,
          0.0,
          0.0,
          0.0,
          0.0,
          0.0,
          0.0,
          0.0,
          0.0,
          0.0
        ],
        "top": 10.630175590515137,
        "bottom": 0.0,
        "median": 0.0,
        "trace": 11.395573616027832
      },
      "mlp": {
        "num_params": 33564672,
        "eigenvalues": [
          3.295858383178711,
          0.24324044585227966,
          0.22216857969760895,
          0.21307872235774994,
          0.18806666135787964,
          8.918975280547414e-11,
          0.0,
          0.0,
          0.0,
          0.0,
          0.0,
          0.0,
          0.0,
          0.0,
          0.0,
          0.0,
          0.0,
          0.0,
          0.0,
          0.0
        ],
        "top": 3.295858383178711,
        "bottom": 0.0,
        "median": 0.0,
        "trace": 4.162412643432617
      }
    },
    {
      "block_idx": 20,
      "attention": {
        "num_params": 16785408,
        "eigenvalues": [
          8.320049285888672,
          0.23582197725772858,
          0.18312565982341766,
          0.16875679790973663,
          0.1488959789276123,
          6.325786006122769e-10,
          0.0,
          0.0,
          0.0,
          0.0,
          0.0,
          0.0,
          0.0,
          0.0,
          0.0,
          0.0,
          0.0,
          0.0,
          0.0,
          0.0
        ],
        "top": 8.320049285888672,
        "bottom": 0.0,
        "median": 0.0,
        "trace": 9.056649208068848
      },
      "mlp": {
        "num_params": 33564672,
        "eigenvalues": [
          3.3013856410980225,
          0.24475626647472382,
          0.21359935402870178,
          0.20387549698352814,
          0.181764617562294,
          5.939729957882278e-11,
          0.0,
          0.0,
          0.0,
          0.0,
          0.0,
          0.0,
          0.0,
          0.0,
          0.0,
          0.0,
          0.0,
          0.0,
          0.0,
          0.0
        ],
        "top": 3.3013856410980225,
        "bottom": 0.0,
        "median": 0.0,
        "trace": 4.145381450653076
      }
    },
    {
      "block_idx": 21,
      "attention": {
        "num_params": 16785408,
        "eigenvalues": [
          6.306280136108398,
          0.2601378560066223,
          0.17916512489318848,
          0.15703220665454865,
          0.13677890598773956,
          2.468228121887961e-10,
          0.0,
          0.0,
          0.0,
          0.0,
          0.0,
          0.0,
          0.0,
          0.0,
          0.0,
          0.0,
          0.0,
          0.0,
          0.0,
          0.0
        ],
        "top": 6.306280136108398,
        "bottom": 0.0,
        "median": 0.0,
        "trace": 7.039394378662109
      },
      "mlp": {
        "num_params": 33564672,
        "eigenvalues": [
          2.7716217041015625,
          0.2166086584329605,
          0.19579066336154938,
          0.1760086566209793,
          0.1611921340227127,
          6.692944809483237e-11,
          0.0,
          0.0,
          0.0,
          0.0,
          0.0,
          0.0,
          0.0,
          0.0,
          0.0,
          0.0,
          0.0,
          0.0,
          0.0,
          0.0
        ],
        "top": 2.7716217041015625,
        "bottom": 0.0,
        "median": 0.0,
        "trace": 3.521221876144409
      }
    },
    {
      "block_idx": 22,
      "attention": {
        "num_params": 16785408,
        "eigenvalues": [
          6.294559955596924,
          0.34161117672920227,
          0.25356364250183105,
          0.23065508902072906,
          0.18772858381271362,
          1.5246262585755233e-10,
          0.0,
          0.0,
          0.0,
          0.0,
          0.0,
          0.0,
          0.0,
          0.0,
          0.0,
          0.0,
          0.0,
          0.0,
          0.0,
          0.0
        ],
        "top": 6.294559955596924,
        "bottom": 0.0,
        "median": 0.0,
        "trace": 7.3081183433532715
      },
      "mlp": {
        "num_params": 33564672,
        "eigenvalues": [
          9.985403060913086,
          0.5459955930709839,
          0.45252346992492676,
          0.4181043207645416,
          0.34050866961479187,
          1.7622611703238533e-10,
          1.1718226486812783e-15,
          0.0,
          0.0,
          0.0,
          0.0,
          0.0,
          0.0,
          0.0,
          0.0,
          0.0,
          0.0,
          0.0,
          0.0,
          0.0
        ],
        "top": 9.985403060913086,
        "bottom": 0.0,
        "median": 0.0,
        "trace": 11.742534637451172
      }
    },
    {
      "block_idx": 23,
      "attention": {
        "num_params": 16785408,
        "eigenvalues": [
          3.108074188232422,
          0.1587950736284256,
          0.14717480540275574,
          0.132616326212883,
          0.11984216421842575,
          5.007389988764821e-11,
          2.2244654323432715e-15,
          0.0,
          0.0,
          0.0,
          0.0,
          0.0,
          0.0,
          0.0,
          0.0,
          0.0,
          0.0,
          0.0,
          0.0,
          0.0
        ],
        "top": 3.108074188232422,
        "bottom": 0.0,
        "median": 0.0,
        "trace": 3.6665024757385254
      },
      "mlp": {
        "num_params": 33564672,
        "eigenvalues": [
          5.287281036376953,
          0.4523847997188568,
          0.32452529668807983,
          0.30201226472854614,
          0.2567709684371948,
          2.8107069449667677e-10,
          0.0,
          0.0,
          0.0,
          0.0,
          0.0,
          0.0,
          0.0,
          0.0,
          0.0,
          0.0,
          0.0,
          0.0,
          0.0,
          0.0
        ],
        "top": 5.287281036376953,
        "bottom": 0.0,
        "median": 0.0,
        "trace": 6.622974395751953
      }
    }
  ],
  "output": {
    "num_params": 104857600,
    "eigenvalues": [
      15.292019844055176,
      1.4488967657089233,
      1.2994295358657837,
      1.223683476448059,
      1.1238442659378052,
      3.8924483081181904e-10,
      1.2768281373062677e-14,
      0.0,
      0.0,
      0.0,
      0.0,
      0.0,
      0.0,
      0.0,
      0.0,
      0.0,
      0.0,
      0.0
    ],
    "top": 15.292019844055176,
    "bottom": 0.0,
    "median": 0.0,
    "trace": 20.387874603271484
  }
}